xevan_hash.cp36-win_amd64.pyd
xevan_hash-0.2.3.dist-info/LICENSE.txt
xevan_hash-0.2.3.dist-info/METADATA
xevan_hash-0.2.3.dist-info/RECORD
xevan_hash-0.2.3.dist-info/WHEEL
xevan_hash-0.2.3.dist-info/top_level.txt
