Metadata-Version: 2.1
Name: xevan-hash
Version: 0.2.3
Summary: Binding for xevan proof of work hashing.
Home-page: https://github.com/ddude1/Xevan_in_Python.git
License: UNKNOWN
Download-URL: https://github.com/ddude1/Xevan_in_Python/archive/0.2.tar.gz
Platform: UNKNOWN
Classifier: Development Status :: 5 - Production/Stable
Classifier: Programming Language :: Python
